{"state":"US","total":0,"candidates":{"59722":"Lib|Phillies|George Phillies","56224":"Ind|Duncan|Richard Duncan","3635":"AIP|Keyes|Alan Keyes","11527":"Lib|Barr|Bob Barr","12619":"Grn|McKinney|Cynthia McKinney","59661":"PCF|Lyttle|Bradford Lyttle","59660":"Obj|Stevens|Thomas Stevens","59207":"New|Polachek|John Joseph Polachek","59208":"AKI|Baldwin|Chuck Baldwin","100013":"NPD|None of these candidates| None of these candidates","3850":"Ind|Nader|Ralph Nader","28726":"RP|Weill|Ted Weill","59886":"Ind|Wamboldt|Jeffrey Wamboldt","302":"LTP|Paul|Ron Paul","3486":"SWP|Harris|James Harris","1918":"Dem|Obama|Barack Obama","7623":"PSL|La Riva|Gloria La Riva","59659":"HQ8|Allen|Jonathan Allen","59593":"Ind|Boss|Jeffrey Boss","1701":"GOP|McCain|John McCain","57761":"Una|McEnulty|Frank McEnulty","51183":"SWP|Calero|Roger Calero","1243":"SPU|Moore|Brian Moore","51335":"BoT|Jay|Charles Jay","51331":"Pro|Amondson|Gene Amondson"},"locals":{"Mississippi":{"name":"Mississippi","electoral":6,"fix":{"Jeff Davis":"Jefferson Davis"},"precincts":{"total":1887,"reporting":0},"races":{"President":{"":{"votes":[{"votes":0,"electoral":0,"id":"1701"},{"votes":0,"electoral":0,"id":"12619"},{"votes":0,"electoral":0,"id":"59208"},{"votes":0,"electoral":0,"id":"1918"},{"votes":0,"electoral":0,"id":"11527"},{"votes":0,"electoral":0,"id":"3850"},{"votes":0,"electoral":0,"id":"28726"}],"final":true}}},"abbr":"MS"},"Oklahoma":{"name":"Oklahoma","electoral":7,"fix":{"LeFlore":"Le Flore"},"precincts":{"total":2231,"reporting":0},"races":{"President":{"":{"votes":[{"votes":0,"electoral":0,"id":"1918"},{"votes":0,"electoral":0,"id":"1701"}],"final":true}}},"abbr":"OK"},"Delaware":{"name":"Delaware","precincts":{"total":339,"reporting":0},"electoral":3,"races":{"President":{"":{"votes":[{"votes":0,"electoral":0,"id":"1701"},{"votes":0,"electoral":0,"id":"12619"},{"votes":0,"electoral":0,"id":"51183"},{"votes":0,"electoral":0,"id":"59208"},{"votes":0,"electoral":0,"id":"1918"},{"votes":0,"electoral":0,"id":"11527"},{"votes":0,"electoral":0,"id":"3850"}],"final":true}}},"abbr":"DE"},"Minnesota":{"name":"Minnesota","electoral":10,"fix":{"Lac Qui Parle":"Lac qui Parle"},"precincts":{"total":4130,"reporting":0},"races":{"President":{"":{"votes":[{"votes":0,"electoral":0,"id":"1701"},{"votes":0,"electoral":0,"id":"12619"},{"votes":0,"electoral":0,"id":"51183"},{"votes":0,"electoral":0,"id":"59208"},{"votes":0,"electoral":0,"id":"1918"},{"votes":0,"electoral":0,"id":"11527"},{"votes":0,"electoral":0,"id":"3850"}],"final":true}}},"abbr":"MN"},"Illinois":{"name":"Illinois","electoral":21,"fix":{"JoDaviess":"Jo Daviess","DeWitt":"De Witt","LaSalle":"La Salle"},"precincts":{"total":11585,"reporting":0},"races":{"President":{"":{"votes":[{"votes":0,"electoral":0,"id":"1701"},{"votes":0,"electoral":0,"id":"59207"},{"votes":0,"electoral":0,"id":"12619"},{"votes":0,"electoral":0,"id":"59208"},{"votes":0,"electoral":0,"id":"1918"},{"votes":0,"electoral":0,"id":"11527"},{"votes":0,"electoral":0,"id":"3850"}],"final":true}}},"abbr":"IL"},"Arkansas":{"name":"Arkansas","electoral":6,"fix":{"Saint Francis":"St. Francis"},"precincts":{"total":2588,"reporting":0},"races":{"President":{"":{"votes":[{"votes":0,"electoral":0,"id":"1701"},{"votes":0,"electoral":0,"id":"7623"},{"votes":0,"electoral":0,"id":"59208"},{"votes":0,"electoral":0,"id":"1918"},{"votes":0,"electoral":0,"id":"11527"},{"votes":0,"electoral":0,"id":"12619"},{"votes":0,"electoral":0,"id":"3850"}],"final":true}}},"abbr":"AR"},"New Mexico":{"name":"New Mexico","electoral":5,"fix":{"DeBaca":"De Baca"},"precincts":{"total":1498,"reporting":0},"races":{"President":{"":{"votes":[{"votes":0,"electoral":0,"id":"1701"},{"votes":0,"electoral":0,"id":"12619"},{"votes":0,"electoral":0,"id":"59208"},{"votes":0,"electoral":0,"id":"1918"},{"votes":0,"electoral":0,"id":"11527"},{"votes":0,"electoral":0,"id":"3850"}]}}},"abbr":"NM"},"Indiana":{"name":"Indiana","precincts":{"total":5230,"reporting":0},"electoral":11,"races":{"President":{"":{"votes":[{"votes":0,"electoral":0,"id":"1918"},{"votes":0,"electoral":0,"id":"11527"},{"votes":0,"electoral":0,"id":"1701"}]}}},"abbr":"IN"},"Maryland":{"name":"Maryland","precincts":{"total":1829,"reporting":0},"electoral":10,"races":{"President":{"":{"votes":[{"votes":0,"electoral":0,"id":"1701"},{"votes":0,"electoral":0,"id":"12619"},{"votes":0,"electoral":0,"id":"59208"},{"votes":0,"electoral":0,"id":"1918"},{"votes":0,"electoral":0,"id":"11527"},{"votes":0,"electoral":0,"id":"3850"}]}}},"abbr":"MD"},"Louisiana":{"name":"Louisiana","electoral":9,"fix":{"DeSoto":"De Soto","Jeff Davis":"Jefferson Davis","LaSalle":"La Salle"},"precincts":{"total":3956,"reporting":0},"races":{"President":{"":{"votes":[{"votes":0,"electoral":0,"id":"1701"},{"votes":0,"electoral":0,"id":"7623"},{"votes":0,"electoral":0,"id":"302"},{"votes":0,"electoral":0,"id":"59208"},{"votes":0,"electoral":0,"id":"3486"},{"votes":0,"electoral":0,"id":"1918"},{"votes":0,"electoral":0,"id":"12619"},{"votes":0,"electoral":0,"id":"3850"},{"votes":0,"electoral":0,"id":"51331"}]}}},"abbr":"LA"},"Idaho":{"name":"Idaho","precincts":{"total":954,"reporting":0},"electoral":4,"races":{"President":{"":{"votes":[{"votes":0,"electoral":0,"id":"1918"},{"votes":0,"electoral":0,"id":"11527"},{"votes":0,"electoral":0,"id":"59208"},{"votes":0,"electoral":0,"id":"3850"},{"votes":0,"electoral":0,"id":"1701"}],"final":true}}},"abbr":"ID"},"Wyoming":{"name":"Wyoming","precincts":{"total":490,"reporting":0},"electoral":3,"races":{"President":{"":{"votes":[{"votes":0,"electoral":0,"id":"1918"},{"votes":0,"electoral":0,"id":"11527"},{"votes":0,"electoral":0,"id":"59208"},{"votes":0,"electoral":0,"id":"3850"},{"votes":0,"electoral":0,"id":"1701"}],"final":true}}},"abbr":"WY"},"Tennessee":{"name":"Tennessee","precincts":{"total":2258,"reporting":0},"electoral":11,"races":{"President":{"":{"votes":[{"votes":0,"electoral":0,"id":"1701"},{"votes":0,"electoral":0,"id":"12619"},{"votes":0,"electoral":0,"id":"59208"},{"votes":0,"electoral":0,"id":"1918"},{"votes":0,"electoral":0,"id":"1243"},{"votes":0,"electoral":0,"id":"11527"},{"votes":0,"electoral":0,"id":"3850"},{"votes":0,"electoral":0,"id":"51335"}]}}},"abbr":"TN"},"Arizona":{"name":"Arizona","precincts":{"total":2239,"reporting":0},"electoral":10,"races":{"President":{"":{"votes":[{"votes":0,"electoral":0,"id":"1918"},{"votes":0,"electoral":0,"id":"11527"},{"votes":0,"electoral":0,"id":"12619"},{"votes":0,"electoral":0,"id":"3850"},{"votes":0,"electoral":0,"id":"1701"}]}}},"abbr":"AZ"},"Iowa":{"name":"Iowa","precincts":{"total":1873,"reporting":0},"electoral":7,"races":{"President":{"":{"votes":[{"votes":0,"electoral":0,"id":"1701"},{"votes":0,"electoral":0,"id":"7623"},{"votes":0,"electoral":0,"id":"59208"},{"votes":0,"electoral":0,"id":"3486"},{"votes":0,"electoral":0,"id":"1918"},{"votes":0,"electoral":0,"id":"1243"},{"votes":0,"electoral":0,"id":"11527"},{"votes":0,"electoral":0,"id":"12619"},{"votes":0,"electoral":0,"id":"3850"}],"final":true}}},"abbr":"IA"},"Michigan":{"name":"Michigan","precincts":{"total":5646,"reporting":0},"electoral":17,"races":{"President":{"":{"votes":[{"votes":0,"electoral":0,"id":"1701"},{"votes":0,"electoral":0,"id":"12619"},{"votes":0,"electoral":0,"id":"59208"},{"votes":0,"electoral":0,"id":"1918"},{"votes":0,"electoral":0,"id":"11527"},{"votes":0,"electoral":0,"id":"3850"}],"final":true}}},"abbr":"MI"},"Kansas":{"name":"Kansas","electoral":6,"precincts":{"total":3298,"reporting":0},"races":{"President":{"":{"votes":[{"votes":0,"electoral":0,"id":"1918"},{"votes":0,"electoral":0,"id":"11527"},{"votes":0,"electoral":0,"id":"59208"},{"votes":0,"electoral":0,"id":"3850"},{"votes":0,"electoral":0,"id":"1701"}]}}},"abbr":"KS","votesby":"district"},"Utah":{"name":"Utah","precincts":{"total":2245,"reporting":0},"electoral":5,"races":{"President":{"":{"votes":[{"votes":0,"electoral":0,"id":"1701"},{"votes":0,"electoral":0,"id":"7623"},{"votes":0,"electoral":0,"id":"59208"},{"votes":0,"electoral":0,"id":"1918"},{"votes":0,"electoral":0,"id":"11527"},{"votes":0,"electoral":0,"id":"12619"},{"votes":0,"electoral":0,"id":"3850"}],"final":true}}},"abbr":"UT"},"Virginia":{"name":"Virginia","electoral":13,"fix":{},"precincts":{"total":2493,"reporting":0},"races":{"President":{"":{"votes":[{"votes":0,"electoral":0,"id":"1701"},{"votes":0,"electoral":0,"id":"12619"},{"votes":0,"electoral":0,"id":"59208"},{"votes":0,"electoral":0,"id":"1918"},{"votes":0,"electoral":0,"id":"11527"},{"votes":0,"electoral":0,"id":"3850"}],"final":true}}},"abbr":"VA"},"Oregon":{"name":"Oregon","precincts":{"total":1000,"reporting":0},"electoral":7,"races":{"President":{"":{"votes":[{"votes":0,"electoral":0,"id":"1701"},{"votes":0,"electoral":0,"id":"12619"},{"votes":0,"electoral":0,"id":"59208"},{"votes":0,"electoral":0,"id":"1918"},{"votes":0,"electoral":0,"id":"11527"},{"votes":0,"electoral":0,"id":"3850"}]}}},"abbr":"OR"},"Connecticut":{"name":"Connecticut","electoral":7,"precincts":{"total":759,"reporting":0},"races":{"President":{"":{"votes":[{"votes":0,"electoral":0,"id":"1918"},{"votes":0,"electoral":0,"id":"3850"},{"votes":0,"electoral":0,"id":"1701"}]}}},"abbr":"CT","votesby":"town"},"Montana":{"name":"Montana","electoral":3,"fix":{"Lewis & Clark":"Lewis and Clark"},"precincts":{"total":863,"reporting":0},"races":{"President":{"":{"votes":[{"votes":0,"electoral":0,"id":"1918"},{"votes":0,"electoral":0,"id":"302"},{"votes":0,"electoral":0,"id":"11527"},{"votes":0,"electoral":0,"id":"3850"},{"votes":0,"electoral":0,"id":"1701"}],"final":true}}},"abbr":"MT"},"California":{"name":"California","precincts":{"total":25429,"reporting":0},"electoral":55,"races":{"President":{"":{"votes":[{"votes":0,"electoral":0,"id":"1701"},{"votes":0,"electoral":0,"id":"12619"},{"votes":0,"electoral":0,"id":"3635"},{"votes":0,"electoral":0,"id":"1918"},{"votes":0,"electoral":0,"id":"11527"},{"votes":0,"electoral":0,"id":"3850"}]}}},"abbr":"CA"},"Massachusetts":{"name":"Massachusetts","electoral":12,"fix":{"Barnstable":"Barnstable Town","Manchester":"Manchester-by-the-Sea"},"precincts":{"total":2168,"reporting":0},"races":{"President":{"":{"votes":[{"votes":0,"electoral":0,"id":"1701"},{"votes":0,"electoral":0,"id":"12619"},{"votes":0,"electoral":0,"id":"59208"},{"votes":0,"electoral":0,"id":"1918"},{"votes":0,"electoral":0,"id":"11527"},{"votes":0,"electoral":0,"id":"3850"}],"final":true}}},"abbr":"MA","votesby":"town"},"West Virginia":{"name":"West Virginia","precincts":{"total":1887,"reporting":0},"electoral":5,"races":{"President":{"":{"votes":[{"votes":0,"electoral":0,"id":"12619"},{"votes":0,"electoral":0,"id":"1918"},{"votes":0,"electoral":0,"id":"59208"},{"votes":0,"electoral":0,"id":"3850"},{"votes":0,"electoral":0,"id":"1701"}],"final":true}}},"abbr":"WV"},"South Carolina":{"name":"South Carolina","precincts":{"total":2291,"reporting":0},"electoral":8,"races":{"President":{"":{"votes":[{"votes":0,"electoral":0,"id":"1701"},{"votes":0,"electoral":0,"id":"12619"},{"votes":0,"electoral":0,"id":"59208"},{"votes":0,"electoral":0,"id":"1918"},{"votes":0,"electoral":0,"id":"11527"},{"votes":0,"electoral":0,"id":"3850"}],"final":true}}},"abbr":"SC"},"New Hampshire":{"name":"New Hampshire","electoral":4,"fix":{"":"Atkinson and Gilmanton Academy"},"precincts":{"total":301,"reporting":0},"races":{"President":{"":{"votes":[{"votes":0,"electoral":0,"id":"59722"},{"votes":0,"electoral":0,"id":"1918"},{"votes":0,"electoral":0,"id":"11527"},{"votes":0,"electoral":0,"id":"3850"},{"votes":0,"electoral":0,"id":"1701"}],"final":true}}},"abbr":"NH","votesby":"town"},"Wisconsin":{"name":"Wisconsin","precincts":{"total":3621,"reporting":0},"electoral":10,"races":{"President":{"":{"votes":[{"votes":0,"electoral":0,"id":"1701"},{"votes":0,"electoral":0,"id":"12619"},{"votes":0,"electoral":0,"id":"59886"},{"votes":0,"electoral":0,"id":"59208"},{"votes":0,"electoral":0,"id":"1918"},{"votes":0,"electoral":0,"id":"1243"},{"votes":0,"electoral":0,"id":"11527"},{"votes":0,"electoral":0,"id":"7623"},{"votes":0,"electoral":0,"id":"3850"}],"final":true}}},"abbr":"WI"},"Vermont":{"name":"Vermont","electoral":3,"precincts":{"total":260,"reporting":0},"races":{"President":{"":{"votes":[{"votes":0,"electoral":0,"id":"1701"},{"votes":0,"electoral":0,"id":"3850"},{"votes":0,"electoral":0,"id":"51183"},{"votes":0,"electoral":0,"id":"59208"},{"votes":0,"electoral":0,"id":"1918"},{"votes":0,"electoral":0,"id":"1243"},{"votes":0,"electoral":0,"id":"11527"},{"votes":0,"electoral":0,"id":"7623"}],"final":true}}},"abbr":"VT","votesby":"town"},"Georgia":{"name":"Georgia","precincts":{"total":3303,"reporting":0},"electoral":15,"races":{"President":{"":{"votes":[{"votes":0,"electoral":0,"id":"1918"},{"votes":0,"electoral":0,"id":"11527"},{"votes":0,"electoral":0,"id":"1701"}],"final":true}}},"abbr":"GA"},"North Dakota":{"name":"North Dakota","precincts":{"total":528,"reporting":0},"electoral":3,"races":{"President":{"":{"votes":[{"votes":0,"electoral":0,"id":"1918"},{"votes":0,"electoral":0,"id":"11527"},{"votes":0,"electoral":0,"id":"59208"},{"votes":0,"electoral":0,"id":"3850"},{"votes":0,"electoral":0,"id":"1701"}]}}},"abbr":"ND"},"Pennsylvania":{"name":"Pennsylvania","precincts":{"total":9284,"reporting":0},"electoral":21,"races":{"President":{"":{"votes":[{"votes":0,"electoral":0,"id":"1918"},{"votes":0,"electoral":0,"id":"11527"},{"votes":0,"electoral":0,"id":"3850"},{"votes":0,"electoral":0,"id":"1701"}],"final":true}}},"abbr":"PA"},"Florida":{"name":"Florida","precincts":{"total":7005,"reporting":0},"electoral":27,"races":{"President":{"":{"votes":[{"votes":0,"electoral":0,"id":"1701"},{"votes":0,"electoral":0,"id":"7623"},{"votes":0,"electoral":0,"id":"3635"},{"votes":0,"electoral":0,"id":"59208"},{"votes":0,"electoral":0,"id":"3486"},{"votes":0,"electoral":0,"id":"1918"},{"votes":0,"electoral":0,"id":"1243"},{"votes":0,"electoral":0,"id":"11527"},{"votes":0,"electoral":0,"id":"3850"},{"votes":0,"electoral":0,"id":"12619"},{"votes":0,"electoral":0,"id":"51335"},{"votes":0,"electoral":0,"id":"59660"},{"votes":0,"electoral":0,"id":"51331"}],"final":true}}},"abbr":"FL"},"Alaska":{"name":"Alaska","precincts":{"total":438,"reporting":0},"electoral":3,"races":{"President":{"":{"votes":[{"votes":0,"electoral":0,"id":"1918"},{"votes":0,"electoral":0,"id":"11527"},{"votes":0,"electoral":0,"id":"59208"},{"votes":0,"electoral":0,"id":"3850"},{"votes":0,"electoral":0,"id":"1701"}]}}},"abbr":"AK"},"Kentucky":{"name":"Kentucky","electoral":8,"fix":{"LaRue":"Larue"},"precincts":{"total":3541,"reporting":0},"races":{"President":{"":{"votes":[{"votes":0,"electoral":0,"id":"1918"},{"votes":0,"electoral":0,"id":"11527"},{"votes":0,"electoral":0,"id":"59208"},{"votes":0,"electoral":0,"id":"3850"},{"votes":0,"electoral":0,"id":"1701"}]}}},"abbr":"KY"},"Hawaii":{"name":"Hawaii","precincts":{"total":338,"reporting":0},"electoral":4,"races":{"President":{"":{"votes":[{"votes":0,"electoral":0,"id":"1701"},{"votes":0,"electoral":0,"id":"12619"},{"votes":0,"electoral":0,"id":"59208"},{"votes":0,"electoral":0,"id":"1918"},{"votes":0,"electoral":0,"id":"11527"},{"votes":0,"electoral":0,"id":"3850"}]}}},"abbr":"HI"},"Nebraska":{"name":"Nebraska","precincts":{"total":1708,"reporting":0},"electoral":5,"races":{"President":{"":{"votes":[{"votes":0,"electoral":0,"id":"1701"},{"votes":0,"electoral":0,"id":"12619"},{"votes":0,"electoral":0,"id":"59208"},{"votes":0,"electoral":0,"id":"1918"},{"votes":0,"electoral":0,"id":"11527"},{"votes":0,"electoral":0,"id":"3850"}],"final":true}}},"abbr":"NE"},"Missouri":{"name":"Missouri","electoral":11,"fix":{"LaClede":"Laclede"},"precincts":{"total":3533,"reporting":0},"races":{"President":{"":{"votes":[{"votes":0,"electoral":0,"id":"1918"},{"votes":0,"electoral":0,"id":"11527"},{"votes":0,"electoral":0,"id":"59208"},{"votes":0,"electoral":0,"id":"3850"},{"votes":0,"electoral":0,"id":"1701"}]}}},"abbr":"MO"},"Ohio":{"name":"Ohio","precincts":{"total":11156,"reporting":0},"electoral":20,"races":{"President":{"":{"votes":[{"votes":0,"electoral":0,"id":"1701"},{"votes":0,"electoral":0,"id":"12619"},{"votes":0,"electoral":0,"id":"56224"},{"votes":0,"electoral":0,"id":"59208"},{"votes":0,"electoral":0,"id":"1918"},{"votes":0,"electoral":0,"id":"1243"},{"votes":0,"electoral":0,"id":"11527"},{"votes":0,"electoral":0,"id":"3850"}],"final":true}}},"abbr":"OH"},"Alabama":{"name":"Alabama","precincts":{"total":2843,"reporting":0},"electoral":9,"races":{"President":{"":{"votes":[{"votes":0,"electoral":0,"id":"1918"},{"votes":0,"electoral":0,"id":"11527"},{"votes":0,"electoral":0,"id":"59208"},{"votes":0,"electoral":0,"id":"3850"},{"votes":0,"electoral":0,"id":"1701"}],"final":true}}},"abbr":"AL"},"New York":{"name":"New York","electoral":31,"fix":{"Brooklyn":"Kings","Staten Island":"Richmond","Saint Lawrence":"St. Lawrence","Manhattan":"New York"},"precincts":{"total":16300,"reporting":0},"races":{"President":{"":{"votes":[{"votes":0,"electoral":0,"id":"1701"},{"votes":0,"electoral":0,"id":"7623"},{"votes":0,"electoral":0,"id":"51183"},{"votes":0,"electoral":0,"id":"1918"},{"votes":0,"electoral":0,"id":"11527"},{"votes":0,"electoral":0,"id":"12619"},{"votes":0,"electoral":0,"id":"3850"}],"final":true}}},"abbr":"NY"},"South Dakota":{"name":"South Dakota","precincts":{"total":799,"reporting":0},"electoral":3,"races":{"President":{"":{"votes":[{"votes":0,"electoral":0,"id":"1918"},{"votes":0,"electoral":0,"id":"11527"},{"votes":0,"electoral":0,"id":"59208"},{"votes":0,"electoral":0,"id":"3850"},{"votes":0,"electoral":0,"id":"1701"}]}}},"abbr":"SD"},"Colorado":{"name":"Colorado","precincts":{"total":3215,"reporting":0},"electoral":9,"races":{"President":{"":{"votes":[{"votes":0,"electoral":0,"id":"1701"},{"votes":0,"electoral":0,"id":"3850"},{"votes":0,"electoral":0,"id":"3635"},{"votes":0,"electoral":0,"id":"59208"},{"votes":0,"electoral":0,"id":"3486"},{"votes":0,"electoral":0,"id":"1918"},{"votes":0,"electoral":0,"id":"1243"},{"votes":0,"electoral":0,"id":"11527"},{"votes":0,"electoral":0,"id":"7623"},{"votes":0,"electoral":0,"id":"59659"},{"votes":0,"electoral":0,"id":"51335"},{"votes":0,"electoral":0,"id":"59661"},{"votes":0,"electoral":0,"id":"59660"},{"votes":0,"electoral":0,"id":"51331"},{"votes":0,"electoral":0,"id":"12619"},{"votes":0,"electoral":0,"id":"57761"}]}}},"abbr":"CO"},"New Jersey":{"name":"New Jersey","precincts":{"total":6296,"reporting":0},"electoral":15,"races":{"President":{"":{"votes":[{"votes":0,"electoral":0,"id":"1701"},{"votes":0,"electoral":0,"id":"7623"},{"votes":0,"electoral":0,"id":"51183"},{"votes":0,"electoral":0,"id":"59208"},{"votes":0,"electoral":0,"id":"1918"},{"votes":0,"electoral":0,"id":"1243"},{"votes":0,"electoral":0,"id":"11527"},{"votes":0,"electoral":0,"id":"12619"},{"votes":0,"electoral":0,"id":"3850"},{"votes":0,"electoral":0,"id":"59593"}],"final":true}}},"abbr":"NJ"},"Washington":{"name":"Washington","precincts":{"total":6719,"reporting":0},"electoral":11,"races":{"President":{"":{"votes":[{"votes":0,"electoral":0,"id":"1701"},{"votes":0,"electoral":0,"id":"7623"},{"votes":0,"electoral":0,"id":"59208"},{"votes":0,"electoral":0,"id":"3486"},{"votes":0,"electoral":0,"id":"1918"},{"votes":0,"electoral":0,"id":"11527"},{"votes":0,"electoral":0,"id":"12619"},{"votes":0,"electoral":0,"id":"3850"}]}}},"abbr":"WA"},"North Carolina":{"name":"North Carolina","precincts":{"total":2962,"reporting":0},"electoral":15,"races":{"President":{"":{"votes":[{"votes":0,"electoral":0,"id":"1918"},{"votes":0,"electoral":0,"id":"11527"},{"votes":0,"electoral":0,"id":"1701"}],"final":true}}},"abbr":"NC"},"District of Columbia":{"name":"District of Columbia","precincts":{"total":143,"reporting":0},"electoral":3,"races":{"President":{"":{"votes":[{"votes":0,"electoral":0,"id":"1918"},{"votes":0,"electoral":0,"id":"12619"},{"votes":0,"electoral":0,"id":"3850"},{"votes":0,"electoral":0,"id":"1701"}],"final":true}}},"abbr":"DC"},"Texas":{"name":"Texas","electoral":34,"fix":{"De Witt":"DeWitt","La Vaca":"Lavaca"},"precincts":{"total":8412,"reporting":0},"races":{"President":{"":{"votes":[{"votes":0,"electoral":0,"id":"1918"},{"votes":0,"electoral":0,"id":"11527"},{"votes":0,"electoral":0,"id":"1701"}],"final":true}}},"abbr":"TX"},"Nevada":{"name":"Nevada","precincts":{"total":2015,"reporting":0},"electoral":5,"races":{"President":{"":{"votes":[{"votes":0,"electoral":0,"id":"1701"},{"votes":0,"electoral":0,"id":"3850"},{"votes":0,"electoral":0,"id":"59208"},{"votes":0,"electoral":0,"id":"1918"},{"votes":0,"electoral":0,"id":"11527"},{"votes":0,"electoral":0,"id":"100013"},{"votes":0,"electoral":0,"id":"12619"}]}}},"abbr":"NV"},"Maine":{"name":"Maine","electoral":4,"fix":{},"precincts":{"total":613,"reporting":0},"races":{"President":{"":{"votes":[{"votes":0,"electoral":0,"id":"1918"},{"votes":0,"electoral":0,"id":"12619"},{"votes":0,"electoral":0,"id":"3850"},{"votes":0,"electoral":0,"id":"1701"}],"final":true}}},"abbr":"ME"},"Rhode Island":{"name":"Rhode Island","precincts":{"total":541,"reporting":0},"electoral":4,"races":{"President":{"":{"votes":[{"votes":0,"electoral":0,"id":"1701"},{"votes":0,"electoral":0,"id":"7623"},{"votes":0,"electoral":0,"id":"59208"},{"votes":0,"electoral":0,"id":"1918"},{"votes":0,"electoral":0,"id":"11527"},{"votes":0,"electoral":0,"id":"12619"},{"votes":0,"electoral":0,"id":"3850"}]}}},"abbr":"RI"}},"totals":{"races":{"President":{"":{"votes":[{"votes":0,"electoral":0,"id":"59722"},{"votes":0,"electoral":0,"id":"56224"},{"votes":0,"electoral":0,"id":"3635"},{"votes":0,"electoral":0,"id":"11527"},{"votes":0,"electoral":0,"id":"12619"},{"votes":0,"electoral":0,"id":"59661"},{"votes":0,"electoral":0,"id":"59660"},{"votes":0,"electoral":0,"id":"59207"},{"votes":0,"electoral":0,"id":"59208"},{"votes":0,"electoral":0,"id":"100013"},{"votes":0,"electoral":0,"id":"3850"},{"votes":0,"electoral":0,"id":"28726"},{"votes":0,"electoral":0,"id":"59886"},{"votes":0,"electoral":0,"id":"302"},{"votes":0,"electoral":0,"id":"3486"},{"votes":0,"electoral":0,"id":"1918"},{"votes":0,"electoral":0,"id":"7623"},{"votes":0,"electoral":0,"id":"59659"},{"votes":0,"electoral":0,"id":"59593"},{"votes":0,"electoral":0,"id":"1701"},{"votes":0,"electoral":0,"id":"57761"},{"votes":0,"electoral":0,"id":"51183"},{"votes":0,"electoral":0,"id":"1243"},{"votes":0,"electoral":0,"id":"51335"},{"votes":0,"electoral":0,"id":"51331"}],"precincts":{"total":0,"reporting":0}}}},"electoral":538}}