{"state":"NE","total":782310,"candidates":
{"12619":"Grn|McKinney|Cynthia McKinney","30014":"Dem|Stoddard|Jay Stoddard","2":"|Yes| Yes","30010":"GOP|Smith|Adrian Smith","1701":"GOP|McCain|John McCain","57811":"Dem|Yashirin|Max Yashirin","51570":"Dem|Kleeb|Scott Kleeb","59208":"AKI|Baldwin|Chuck Baldwin","445":"GOP|Johanns|Mike Johanns","51569":"Dem|Esch|Jim Esch","1918":"Dem|Obama|Barack Obama","49989":"GOP|Fortenberry|Jeff Fortenberry","11527":"Lib|Barr|Bob Barr","50446":"Grn|Larrick|Steve Larrick","3850":"Ind|Nader|Ralph Nader","29993":"Neb|Rosberg|Kelly Rosberg","231":"GOP|Terry|Lee Terry","3":"|No| No"},
"locals":
{"Colfax":
{"fips":"31037","races":
{"President":
{"":
{"votes":[
{"votes":2014,"id":"1701"},
{"votes":1125,"id":"1918"},
{"votes":21,"id":"3850"},
{"votes":16,"id":"59208"},
{"votes":10,"id":"11527"},
{"votes":4,"id":"12619"}],
"total":3190,"final":"1701"}}},
"precincts":
{"total":6,"reporting":6},
"name":"Colfax"},
"Holt":
{"fips":"31089","races":
{"President":
{"":
{"votes":[
{"votes":3663,"id":"1701"},
{"votes":1065,"id":"1918"},
{"votes":39,"id":"59208"},
{"votes":35,"id":"3850"},
{"votes":31,"id":"11527"},
{"votes":13,"id":"12619"}],
"total":4846,"final":"1701"}}},
"precincts":
{"total":14,"reporting":14},
"name":"Holt"},
"Furnas":
{"fips":"31065","races":
{"President":
{"":
{"votes":[
{"votes":1725,"id":"1701"},
{"votes":556,"id":"1918"},
{"votes":21,"id":"3850"},
{"votes":18,"id":"59208"},
{"votes":5,"id":"11527"},
{"votes":1,"id":"12619"}],
"total":2326,"final":"1701"}}},
"precincts":
{"total":8,"reporting":8},
"name":"Furnas"},
"Frontier":
{"fips":"31063","races":
{"President":
{"":
{"votes":[
{"votes":1030,"id":"1701"},
{"votes":348,"id":"1918"},
{"votes":7,"id":"3850"},
{"votes":5,"id":"11527"},
{"votes":4,"id":"12619"},
{"votes":3,"id":"59208"}],
"total":1397,"final":"1701"}}},
"precincts":
{"total":5,"reporting":5},
"name":"Frontier"},
"Otoe":
{"fips":"31131","races":
{"President":
{"":
{"votes":[
{"votes":3991,"id":"1701"},
{"votes":2893,"id":"1918"},
{"votes":49,"id":"3850"},
{"votes":33,"id":"59208"},
{"votes":25,"id":"11527"},
{"votes":9,"id":"12619"}],
"total":7000,"final":"1701"}}},
"precincts":
{"total":17,"reporting":17},
"name":"Otoe"},
"Wayne":
{"fips":"31179","races":
{"President":
{"":
{"votes":[
{"votes":2503,"id":"1701"},
{"votes":1249,"id":"1918"},
{"votes":21,"id":"3850"},
{"votes":16,"id":"59208"},
{"votes":11,"id":"11527"},
{"votes":8,"id":"12619"}],
"total":3808,"final":"1701"}}},
"precincts":
{"total":11,"reporting":11},
"name":"Wayne"},
"Dixon":
{"fips":"31051","races":
{"President":
{"":
{"votes":[
{"votes":1785,"id":"1701"},
{"votes":946,"id":"1918"},
{"votes":24,"id":"59208"},
{"votes":22,"id":"3850"},
{"votes":5,"id":"11527"},
{"votes":3,"id":"12619"}],
"total":2785,"final":"1701"}}},
"precincts":
{"total":12,"reporting":12},
"name":"Dixon"},
"Hooker":
{"fips":"31091","races":
{"President":
{"":
{"votes":[
{"votes":355,"id":"1701"},
{"votes":75,"id":"1918"},
{"votes":3,"id":"59208"},
{"votes":2,"id":"12619"},
{"votes":2,"id":"11527"},
{"votes":1,"id":"3850"}],
"total":438,"final":"1701"}}},
"precincts":
{"total":2,"reporting":2},
"name":"Hooker"},
"Dodge":
{"fips":"31053","races":
{"President":
{"":
{"votes":[
{"votes":8482,"id":"1701"},
{"votes":6587,"id":"1918"},
{"votes":110,"id":"3850"},
{"votes":56,"id":"59208"},
{"votes":54,"id":"11527"},
{"votes":20,"id":"12619"}],
"total":15309,"final":"1701"}}},
"precincts":
{"total":32,"reporting":32},
"name":"Dodge"},
"Brown":
{"fips":"31017","races":
{"President":
{"":
{"votes":[
{"votes":1208,"id":"1701"},
{"votes":311,"id":"1918"},
{"votes":27,"id":"59208"},
{"votes":13,"id":"3850"},
{"votes":7,"id":"11527"},
{"votes":1,"id":"12619"}],
"total":1567,"final":"1701"}}},
"precincts":
{"total":4,"reporting":4},
"name":"Brown"},
"Stanton":
{"fips":"31167","races":
{"President":
{"":
{"votes":[
{"votes":1772,"id":"1701"},
{"votes":657,"id":"1918"},
{"votes":18,"id":"59208"},
{"votes":10,"id":"3850"},
{"votes":8,"id":"11527"},
{"votes":1,"id":"12619"}],
"total":2466,"final":"1701"}}},
"precincts":
{"total":16,"reporting":16},
"name":"Stanton"},
"Custer":
{"fips":"31041","races":
{"President":
{"":
{"votes":[
{"votes":4220,"id":"1701"},
{"votes":1178,"id":"1918"},
{"votes":33,"id":"3850"},
{"votes":24,"id":"59208"},
{"votes":22,"id":"11527"},
{"votes":5,"id":"12619"}],
"total":5482,"final":"1701"}}},
"precincts":
{"total":39,"reporting":39},
"name":"Custer"},
"Kearney":
{"fips":"31099","races":
{"President":
{"":
{"votes":[
{"votes":2217,"id":"1701"},
{"votes":870,"id":"1918"},
{"votes":24,"id":"3850"},
{"votes":14,"id":"59208"},
{"votes":6,"id":"11527"},
{"votes":2,"id":"12619"}],
"total":3133,"final":"1701"}}},
"precincts":
{"total":13,"reporting":13},
"name":"Kearney"},
"Burt":
{"fips":"31021","races":
{"President":
{"":
{"votes":[
{"votes":1895,"id":"1701"},
{"votes":1406,"id":"1918"},
{"votes":26,"id":"3850"},
{"votes":23,"id":"59208"},
{"votes":8,"id":"11527"},
{"votes":2,"id":"12619"}],
"total":3360,"final":"1701"}}},
"precincts":
{"total":11,"reporting":11},
"name":"Burt"},
"York":
{"fips":"31185","races":
{"President":
{"":
{"votes":[
{"votes":4807,"id":"1701"},
{"votes":1594,"id":"1918"},
{"votes":35,"id":"59208"},
{"votes":29,"id":"3850"},
{"votes":14,"id":"11527"},
{"votes":10,"id":"12619"}],
"total":6489,"final":"1701"}}},
"precincts":
{"total":15,"reporting":15},
"name":"York"},
"Grant":
{"fips":"31075","races":
{"President":
{"":
{"votes":[
{"votes":321,"id":"1701"},
{"votes":41,"id":"1918"},
{"votes":3,"id":"3850"},
{"votes":2,"id":"59208"},
{"votes":1,"id":"12619"},
{"votes":0,"id":"11527"}],
"total":368,"final":"1701"}}},
"precincts":
{"total":7,"reporting":7},
"name":"Grant"},
"Hitchcock":
{"fips":"31087","races":
{"President":
{"":
{"votes":[
{"votes":997,"id":"1701"},
{"votes":346,"id":"1918"},
{"votes":10,"id":"59208"},
{"votes":9,"id":"3850"},
{"votes":6,"id":"11527"},
{"votes":1,"id":"12619"}],
"total":1369,"final":"1701"}}},
"precincts":
{"total":4,"reporting":4},
"name":"Hitchcock"},
"Loup":
{"fips":"31115","races":
{"President":
{"":
{"votes":[
{"votes":302,"id":"1701"},
{"votes":86,"id":"1918"},
{"votes":1,"id":"12619"},
{"votes":1,"id":"11527"},
{"votes":1,"id":"3850"},
{"votes":0,"id":"59208"}],
"total":391,"final":"1701"}}},
"precincts":
{"total":1,"reporting":1},
"name":"Loup"},
"Morrill":
{"fips":"31123","races":
{"President":
{"":
{"votes":[
{"votes":1700,"id":"1701"},
{"votes":546,"id":"1918"},
{"votes":26,"id":"59208"},
{"votes":22,"id":"3850"},
{"votes":7,"id":"12619"},
{"votes":7,"id":"11527"}],
"total":2308,"final":"1701"}}},
"precincts":
{"total":10,"reporting":10},
"name":"Morrill"},
"Box Butte":
{"fips":"31013","races":
{"President":
{"":
{"votes":[
{"votes":2888,"id":"1701"},
{"votes":1844,"id":"1918"},
{"votes":68,"id":"3850"},
{"votes":32,"id":"59208"},
{"votes":25,"id":"11527"},
{"votes":11,"id":"12619"}],
"total":4868,"final":"1701"}}},
"precincts":
{"total":9,"reporting":9},
"name":"Box Butte"},
"Webster":
{"fips":"31181","races":
{"President":
{"":
{"votes":[
{"votes":1323,"id":"1701"},
{"votes":550,"id":"1918"},
{"votes":16,"id":"3850"},
{"votes":7,"id":"59208"},
{"votes":5,"id":"12619"},
{"votes":4,"id":"11527"}],
"total":1905,"final":"1701"}}},
"precincts":
{"total":6,"reporting":6},
"name":"Webster"},
"Seward":
{"fips":"31159","races":
{"President":
{"":
{"votes":[
{"votes":4596,"id":"1701"},
{"votes":2671,"id":"1918"},
{"votes":57,"id":"3850"},
{"votes":51,"id":"59208"},
{"votes":34,"id":"11527"},
{"votes":8,"id":"12619"}],
"total":7417,"final":"1701"}}},
"precincts":
{"total":17,"reporting":17},
"name":"Seward"},
"Kimball":
{"fips":"31105","races":
{"President":
{"":
{"votes":[
{"votes":1328,"id":"1701"},
{"votes":427,"id":"1918"},
{"votes":16,"id":"3850"},
{"votes":4,"id":"59208"},
{"votes":3,"id":"12619"},
{"votes":1,"id":"11527"}],
"total":1779,"final":"1701"}}},
"precincts":
{"total":6,"reporting":6},
"name":"Kimball"},
"Thomas":
{"fips":"31171","races":
{"President":
{"":
{"votes":[
{"votes":331,"id":"1701"},
{"votes":51,"id":"1918"},
{"votes":4,"id":"3850"},
{"votes":2,"id":"59208"},
{"votes":1,"id":"12619"},
{"votes":1,"id":"11527"}],
"total":390,"final":"1701"}}},
"precincts":
{"total":1,"reporting":1},
"name":"Thomas"},
"Saunders":
{"fips":"31155","races":
{"President":
{"":
{"votes":[
{"votes":6132,"id":"1701"},
{"votes":3739,"id":"1918"},
{"votes":90,"id":"3850"},
{"votes":49,"id":"59208"},
{"votes":47,"id":"11527"},
{"votes":17,"id":"12619"}],
"total":10074,"final":"1701"}}},
"precincts":
{"total":19,"reporting":19},
"name":"Saunders"},
"Platte":
{"fips":"31141","races":
{"President":
{"":
{"votes":[
{"votes":9279,"id":"1701"},
{"votes":3734,"id":"1918"},
{"votes":75,"id":"3850"},
{"votes":74,"id":"59208"},
{"votes":46,"id":"11527"},
{"votes":14,"id":"12619"}],
"total":13222,"final":"1701"}}},
"precincts":
{"total":31,"reporting":31},
"name":"Platte"},
"Washington":
{"fips":"31177","races":
{"President":
{"":
{"votes":[
{"votes":6409,"id":"1701"},
{"votes":3681,"id":"1918"},
{"votes":69,"id":"3850"},
{"votes":40,"id":"59208"},
{"votes":40,"id":"11527"},
{"votes":20,"id":"12619"}],
"total":10259,"final":"1701"}}},
"precincts":
{"total":16,"reporting":16},
"name":"Washington"},
"Dawes":
{"fips":"31045","races":
{"President":
{"":
{"votes":[
{"votes":2330,"id":"1701"},
{"votes":1245,"id":"1918"},
{"votes":55,"id":"3850"},
{"votes":25,"id":"59208"},
{"votes":17,"id":"11527"},
{"votes":5,"id":"12619"}],
"total":3677,"final":"1701"}}},
"precincts":
{"total":12,"reporting":12},
"name":"Dawes"},
"Dakota":
{"fips":"31043","races":
{"President":
{"":
{"votes":[
{"votes":3255,"id":"1701"},
{"votes":2966,"id":"1918"},
{"votes":49,"id":"3850"},
{"votes":30,"id":"59208"},
{"votes":7,"id":"12619"},
{"votes":7,"id":"11527"}],
"total":6314,"final":"1701"}}},
"precincts":
{"total":14,"reporting":14},
"name":"Dakota"},
"Polk":
{"fips":"31143","races":
{"President":
{"":
{"votes":[
{"votes":1810,"id":"1701"},
{"votes":665,"id":"1918"},
{"votes":16,"id":"59208"},
{"votes":15,"id":"3850"},
{"votes":8,"id":"11527"},
{"votes":6,"id":"12619"}],
"total":2520,"final":"1701"}}},
"precincts":
{"total":7,"reporting":7},
"name":"Polk"},
"Chase":
{"fips":"31029","races":
{"President":
{"":
{"votes":[
{"votes":1466,"id":"1701"},
{"votes":341,"id":"1918"},
{"votes":7,"id":"11527"},
{"votes":7,"id":"3850"},
{"votes":5,"id":"59208"},
{"votes":3,"id":"12619"}],
"total":1829,"final":"1701"}}},
"precincts":
{"total":6,"reporting":6},
"name":"Chase"},
"Deuel":
{"fips":"31049","races":
{"President":
{"":
{"votes":[
{"votes":732,"id":"1701"},
{"votes":243,"id":"1918"},
{"votes":8,"id":"59208"},
{"votes":5,"id":"11527"},
{"votes":5,"id":"3850"},
{"votes":0,"id":"12619"}],
"total":993,"final":"1701"}}},
"precincts":
{"total":3,"reporting":3},
"name":"Deuel"},
"Howard":
{"fips":"31093","races":
{"President":
{"":
{"votes":[
{"votes":1847,"id":"1701"},
{"votes":1083,"id":"1918"},
{"votes":21,"id":"3850"},
{"votes":17,"id":"59208"},
{"votes":10,"id":"12619"},
{"votes":8,"id":"11527"}],
"total":2986,"final":"1701"}}},
"precincts":
{"total":9,"reporting":9},
"name":"Howard"},
"Sheridan":
{"fips":"31161","races":
{"President":
{"":
{"votes":[
{"votes":1934,"id":"1701"},
{"votes":451,"id":"1918"},
{"votes":29,"id":"59208"},
{"votes":13,"id":"11527"},
{"votes":11,"id":"3850"},
{"votes":0,"id":"12619"}],
"total":2438,"final":"1701"}}},
"precincts":
{"total":9,"reporting":9},
"name":"Sheridan"},
"Jefferson":
{"fips":"31095","races":
{"President":
{"":
{"votes":[
{"votes":2091,"id":"1701"},
{"votes":1504,"id":"1918"},
{"votes":33,"id":"3850"},
{"votes":18,"id":"59208"},
{"votes":9,"id":"11527"},
{"votes":5,"id":"12619"}],
"total":3660,"final":"1701"}}},
"precincts":
{"total":11,"reporting":11},
"name":"Jefferson"},
"Cheyenne":
{"fips":"31033","races":
{"President":
{"":
{"votes":[
{"votes":3284,"id":"1701"},
{"votes":1064,"id":"1918"},
{"votes":25,"id":"3850"},
{"votes":18,"id":"59208"},
{"votes":17,"id":"11527"},
{"votes":5,"id":"12619"}],
"total":4413,"final":"1701"}}},
"precincts":
{"total":10,"reporting":10},
"name":"Cheyenne"},
"Butler":
{"fips":"31023","races":
{"President":
{"":
{"votes":[
{"votes":2534,"id":"1701"},
{"votes":1175,"id":"1918"},
{"votes":38,"id":"3850"},
{"votes":24,"id":"59208"},
{"votes":11,"id":"11527"},
{"votes":7,"id":"12619"}],
"total":3789,"final":"1701"}}},
"precincts":
{"total":21,"reporting":21},
"name":"Butler"},
"McPherson":
{"fips":"31117","races":
{"President":
{"":
{"votes":[
{"votes":240,"id":"1701"},
{"votes":45,"id":"1918"},
{"votes":4,"id":"11527"},
{"votes":2,"id":"59208"},
{"votes":2,"id":"3850"},
{"votes":0,"id":"12619"}],
"total":293,"final":"1701"}}},
"precincts":
{"total":1,"reporting":1},
"name":"McPherson"},
"Boyd":
{"fips":"31015","races":
{"President":
{"":
{"votes":[
{"votes":839,"id":"1701"},
{"votes":250,"id":"1918"},
{"votes":10,"id":"59208"},
{"votes":8,"id":"3850"},
{"votes":2,"id":"11527"},
{"votes":0,"id":"12619"}],
"total":1109,"final":"1701"}}},
"precincts":
{"total":4,"reporting":4},
"name":"Boyd"},
"Sherman":
{"fips":"31163","races":
{"President":
{"":
{"votes":[
{"votes":940,"id":"1701"},
{"votes":583,"id":"1918"},
{"votes":15,"id":"59208"},
{"votes":15,"id":"3850"},
{"votes":2,"id":"12619"},
{"votes":1,"id":"11527"}],
"total":1556,"final":"1701"}}},
"precincts":
{"total":7,"reporting":7},
"name":"Sherman"},
"Hamilton":
{"fips":"31081","races":
{"President":
{"":
{"votes":[
{"votes":3362,"id":"1701"},
{"votes":1322,"id":"1918"},
{"votes":29,"id":"3850"},
{"votes":23,"id":"59208"},
{"votes":8,"id":"11527"},
{"votes":0,"id":"12619"}],
"total":4744,"final":"1701"}}},
"precincts":
{"total":12,"reporting":12},
"name":"Hamilton"},
"Cuming":
{"fips":"31039","races":
{"President":
{"":
{"votes":[
{"votes":2701,"id":"1701"},
{"votes":1255,"id":"1918"},
{"votes":34,"id":"59208"},
{"votes":31,"id":"3850"},
{"votes":8,"id":"11527"},
{"votes":1,"id":"12619"}],
"total":4030,"final":"1701"}}},
"precincts":
{"total":9,"reporting":9},
"name":"Cuming"},
"Keith":
{"fips":"31101","races":
{"President":
{"":
{"votes":[
{"votes":2917,"id":"1701"},
{"votes":965,"id":"1918"},
{"votes":14,"id":"3850"},
{"votes":13,"id":"59208"},
{"votes":9,"id":"11527"},
{"votes":5,"id":"12619"}],
"total":3923,"final":"1701"}}},
"precincts":
{"total":12,"reporting":12},
"name":"Keith"},
"Sioux":
{"fips":"31165","races":
{"President":
{"":
{"votes":[
{"votes":600,"id":"1701"},
{"votes":116,"id":"1918"},
{"votes":5,"id":"59208"},
{"votes":5,"id":"3850"},
{"votes":2,"id":"11527"},
{"votes":0,"id":"12619"}],
"total":728,"final":"1701"}}},
"precincts":
{"total":2,"reporting":2},
"name":"Sioux"},
"Johnson":
{"fips":"31097","races":
{"President":
{"":
{"votes":[
{"votes":1139,"id":"1701"},
{"votes":914,"id":"1918"},
{"votes":23,"id":"3850"},
{"votes":10,"id":"11527"},
{"votes":6,"id":"59208"},
{"votes":3,"id":"12619"}],
"total":2095,"final":"1701"}}},
"precincts":
{"total":9,"reporting":9},
"name":"Johnson"},
"Arthur":
{"fips":"31005","races":
{"President":
{"":
{"votes":[
{"votes":217,"id":"1701"},
{"votes":39,"id":"1918"},
{"votes":3,"id":"59208"},
{"votes":2,"id":"3850"},
{"votes":1,"id":"11527"},
{"votes":0,"id":"12619"}],
"total":262,"final":"1701"}}},
"precincts":
{"total":1,"reporting":1},
"name":"Arthur"},
"Rock":
{"fips":"31149","races":
{"President":
{"":
{"votes":[
{"votes":635,"id":"1701"},
{"votes":136,"id":"1918"},
{"votes":12,"id":"59208"},
{"votes":2,"id":"3850"},
{"votes":1,"id":"12619"},
{"votes":1,"id":"11527"}],
"total":787,"final":"1701"}}},
"precincts":
{"total":6,"reporting":6},
"name":"Rock"},
"Buffalo":
{"fips":"31019","races":
{"President":
{"":
{"votes":[
{"votes":12920,"id":"1701"},
{"votes":5768,"id":"1918"},
{"votes":110,"id":"3850"},
{"votes":77,"id":"59208"},
{"votes":52,"id":"11527"},
{"votes":17,"id":"12619"}],
"total":18944,"final":"1701"}}},
"precincts":
{"total":34,"reporting":34},
"name":"Buffalo"},
"Madison":
{"fips":"31119","races":
{"President":
{"":
{"votes":[
{"votes":9542,"id":"1701"},
{"votes":4076,"id":"1918"},
{"votes":88,"id":"3850"},
{"votes":63,"id":"59208"},
{"votes":42,"id":"11527"},
{"votes":9,"id":"12619"}],
"total":13820,"final":"1701"}}},
"precincts":
{"total":24,"reporting":24},
"name":"Madison"},
"Sarpy":
{"fips":"31153","races":
{"President":
{"":
{"votes":[
{"votes":38443,"id":"1701"},
{"votes":27663,"id":"1918"},
{"votes":395,"id":"3850"},
{"votes":295,"id":"11527"},
{"votes":185,"id":"59208"},
{"votes":58,"id":"12619"}],
"total":67039,"final":"1701"}}},
"precincts":
{"total":88,"reporting":88},
"name":"Sarpy"},
"Red Willow":
{"fips":"31145","races":
{"President":
{"":
{"votes":[
{"votes":3748,"id":"1701"},
{"votes":1216,"id":"1918"},
{"votes":29,"id":"3850"},
{"votes":26,"id":"59208"},
{"votes":15,"id":"11527"},
{"votes":7,"id":"12619"}],
"total":5041,"final":"1701"}}},
"precincts":
{"total":16,"reporting":16},
"name":"Red Willow"},
"Blaine":
{"fips":"31009","races":
{"President":
{"":
{"votes":[
{"votes":266,"id":"1701"},
{"votes":43,"id":"1918"},
{"votes":3,"id":"3850"},
{"votes":2,"id":"59208"},
{"votes":2,"id":"11527"},
{"votes":0,"id":"12619"}],
"total":316,"final":"1701"}}},
"precincts":
{"total":1,"reporting":1},
"name":"Blaine"},
"Dawson":
{"fips":"31047","races":
{"President":
{"":
{"votes":[
{"votes":5368,"id":"1701"},
{"votes":2352,"id":"1918"},
{"votes":49,"id":"3850"},
{"votes":31,"id":"59208"},
{"votes":26,"id":"11527"},
{"votes":5,"id":"12619"}],
"total":7831,"final":"1701"}}},
"precincts":
{"total":20,"reporting":20},
"name":"Dawson"},
"Saline":
{"fips":"31151","races":
{"President":
{"":
{"votes":[
{"votes":2597,"id":"1918"},
{"votes":2373,"id":"1701"},
{"votes":58,"id":"3850"},
{"votes":25,"id":"59208"},
{"votes":20,"id":"11527"},
{"votes":11,"id":"12619"}],
"total":5084,"final":"1701"}}},
"precincts":
{"total":13,"reporting":13},
"name":"Saline"},
"Cass":
{"fips":"31025","races":
{"President":
{"":
{"votes":[
{"votes":7076,"id":"1701"},
{"votes":4709,"id":"1918"},
{"votes":79,"id":"3850"},
{"votes":53,"id":"11527"},
{"votes":48,"id":"59208"},
{"votes":8,"id":"12619"}],
"total":11973,"final":"1701"}}},
"precincts":
{"total":30,"reporting":30},
"name":"Cass"},
"Nemaha":
{"fips":"31127","races":
{"President":
{"":
{"votes":[
{"votes":2090,"id":"1701"},
{"votes":1207,"id":"1918"},
{"votes":35,"id":"3850"},
{"votes":24,"id":"59208"},
{"votes":15,"id":"11527"},
{"votes":5,"id":"12619"}],
"total":3376,"final":"1701"}}},
"precincts":
{"total":10,"reporting":10},
"name":"Nemaha"},
"Clay":
{"fips":"31035","races":
{"President":
{"":
{"votes":[
{"votes":2134,"id":"1701"},
{"votes":761,"id":"1918"},
{"votes":27,"id":"3850"},
{"votes":24,"id":"59208"},
{"votes":7,"id":"11527"},
{"votes":3,"id":"12619"}],
"total":2956,"final":"1701"}}},
"precincts":
{"total":12,"reporting":12},
"name":"Clay"},
"Gage":
{"fips":"31067","races":
{"President":
{"":
{"votes":[
{"votes":5389,"id":"1701"},
{"votes":4405,"id":"1918"},
{"votes":98,"id":"3850"},
{"votes":51,"id":"11527"},
{"votes":45,"id":"59208"},
{"votes":17,"id":"12619"}],
"total":10005,"final":"1701"}}},
"precincts":
{"total":28,"reporting":28},
"name":"Gage"},
"Wheeler":
{"fips":"31183","races":
{"President":
{"":
{"votes":[
{"votes":334,"id":"1701"},
{"votes":96,"id":"1918"},
{"votes":3,"id":"59208"},
{"votes":2,"id":"3850"},
{"votes":1,"id":"12619"},
{"votes":1,"id":"11527"}],
"total":437,"final":"1701"}}},
"precincts":
{"total":2,"reporting":2},
"name":"Wheeler"},
"Cedar":
{"fips":"31027","races":
{"President":
{"":
{"votes":[
{"votes":2912,"id":"1701"},
{"votes":1187,"id":"1918"},
{"votes":36,"id":"3850"},
{"votes":22,"id":"59208"},
{"votes":4,"id":"11527"},
{"votes":3,"id":"12619"}],
"total":4164,"final":"1701"}}},
"precincts":
{"total":17,"reporting":17},
"name":"Cedar"},
"Dundy":
{"fips":"31057","races":
{"President":
{"":
{"votes":[
{"votes":783,"id":"1701"},
{"votes":218,"id":"1918"},
{"votes":7,"id":"59208"},
{"votes":6,"id":"3850"},
{"votes":3,"id":"11527"},
{"votes":2,"id":"12619"}],
"total":1019,"final":"1701"}}},
"precincts":
{"total":4,"reporting":4},
"name":"Dundy"},
"Lincoln":
{"fips":"31111","races":
{"President":
{"":
{"votes":[
{"votes":10609,"id":"1701"},
{"votes":4937,"id":"1918"},
{"votes":150,"id":"3850"},
{"votes":107,"id":"59208"},
{"votes":50,"id":"11527"},
{"votes":21,"id":"12619"}],
"total":15874,"final":"1701"}}},
"precincts":
{"total":28,"reporting":28},
"name":"Lincoln"},
"Adams":
{"fips":"31001","races":
{"President":
{"":
{"votes":[
{"votes":8163,"id":"1701"},
{"votes":4624,"id":"1918"},
{"votes":98,"id":"3850"},
{"votes":61,"id":"59208"},
{"votes":40,"id":"11527"},
{"votes":16,"id":"12619"}],
"total":13002,"final":"1701"}}},
"precincts":
{"total":28,"reporting":28},
"name":"Adams"},
"Hayes":
{"fips":"31085","races":
{"President":
{"":
{"votes":[
{"votes":460,"id":"1701"},
{"votes":85,"id":"1918"},
{"votes":4,"id":"59208"},
{"votes":2,"id":"11527"},
{"votes":1,"id":"12619"},
{"votes":0,"id":"3850"}],
"total":552,"final":"1701"}}},
"precincts":
{"total":3,"reporting":3},
"name":"Hayes"},
"Harlan":
{"fips":"31083","races":
{"President":
{"":
{"votes":[
{"votes":1327,"id":"1701"},
{"votes":399,"id":"1918"},
{"votes":20,"id":"3850"},
{"votes":9,"id":"11527"},
{"votes":5,"id":"59208"},
{"votes":1,"id":"12619"}],
"total":1761,"final":"1701"}}},
"precincts":
{"total":9,"reporting":9},
"name":"Harlan"},
"Franklin":
{"fips":"31061","races":
{"President":
{"":
{"votes":[
{"votes":1078,"id":"1701"},
{"votes":442,"id":"1918"},
{"votes":13,"id":"3850"},
{"votes":7,"id":"59208"},
{"votes":4,"id":"11527"},
{"votes":3,"id":"12619"}],
"total":1547,"final":"1701"}}},
"precincts":
{"total":5,"reporting":5},
"name":"Franklin"},
"Richardson":
{"fips":"31147","races":
{"President":
{"":
{"votes":[
{"votes":1880,"id":"1701"},
{"votes":1121,"id":"1918"},
{"votes":38,"id":"3850"},
{"votes":19,"id":"59208"},
{"votes":12,"id":"11527"},
{"votes":8,"id":"12619"}],
"total":3078,"final":"1701"}}},
"precincts":
{"total":15,"reporting":15},
"name":"Richardson"},
"Antelope":
{"fips":"31003","races":
{"President":
{"":
{"votes":[
{"votes":2367,"id":"1701"},
{"votes":754,"id":"1918"},
{"votes":16,"id":"3850"},
{"votes":10,"id":"59208"},
{"votes":9,"id":"11527"},
{"votes":1,"id":"12619"}],
"total":3157,"final":"1701"}}},
"precincts":
{"total":14,"reporting":14},
"name":"Antelope"},
"Fillmore":
{"fips":"31059","races":
{"President":
{"":
{"votes":[
{"votes":1907,"id":"1701"},
{"votes":953,"id":"1918"},
{"votes":24,"id":"3850"},
{"votes":18,"id":"59208"},
{"votes":7,"id":"11527"},
{"votes":5,"id":"12619"}],
"total":2914,"final":"1701"}}},
"precincts":
{"total":16,"reporting":16},
"name":"Fillmore"},
"Greeley":
{"fips":"31077","races":
{"President":
{"":
{"votes":[
{"votes":714,"id":"1701"},
{"votes":457,"id":"1918"},
{"votes":11,"id":"3850"},
{"votes":6,"id":"11527"},
{"votes":5,"id":"59208"},
{"votes":4,"id":"12619"}],
"total":1197,"final":"1701"}}},
"precincts":
{"total":5,"reporting":5},
"name":"Greeley"},
"Lancaster":
{"fips":"31109","races":
{"President":
{"":
{"votes":[
{"votes":63464,"id":"1918"},
{"votes":57925,"id":"1701"},
{"votes":852,"id":"3850"},
{"votes":378,"id":"11527"},
{"votes":324,"id":"59208"},
{"votes":218,"id":"12619"}],
"total":123161,"final":"1701"}}},
"precincts":
{"total":223,"reporting":223},
"name":"Lancaster"},
"Cherry":
{"fips":"31031","races":
{"President":
{"":
{"votes":[
{"votes":2360,"id":"1701"},
{"votes":599,"id":"1918"},
{"votes":44,"id":"59208"},
{"votes":35,"id":"3850"},
{"votes":10,"id":"11527"},
{"votes":2,"id":"12619"}],
"total":3050,"final":"1701"}}},
"precincts":
{"total":21,"reporting":21},
"name":"Cherry"},
"Douglas":
{"fips":"31055","races":
{"President":
{"":
{"votes":[
{"votes":112460,"id":"1918"},
{"votes":104030,"id":"1701"},
{"votes":1278,"id":"3850"},
{"votes":756,"id":"11527"},
{"votes":437,"id":"59208"},
{"votes":263,"id":"12619"}],
"total":219224,"final":"1701"}}},
"precincts":
{"total":352,"reporting":352},
"name":"Douglas"},
"Valley":
{"fips":"31175","races":
{"President":
{"":
{"votes":[
{"votes":1647,"id":"1701"},
{"votes":704,"id":"1918"},
{"votes":21,"id":"3850"},
{"votes":17,"id":"59208"},
{"votes":11,"id":"11527"},
{"votes":3,"id":"12619"}],
"total":2403,"final":"1701"}}},
"precincts":
{"total":8,"reporting":8},
"name":"Valley"},
"Garden":
{"fips":"31069","races":
{"President":
{"":
{"votes":[
{"votes":844,"id":"1701"},
{"votes":283,"id":"1918"},
{"votes":6,"id":"3850"},
{"votes":5,"id":"59208"},
{"votes":0,"id":"12619"},
{"votes":0,"id":"11527"}],
"total":1138,"final":"1701"}}},
"precincts":
{"total":5,"reporting":5},
"name":"Garden"},
"Phelps":
{"fips":"31137","races":
{"President":
{"":
{"votes":[
{"votes":3340,"id":"1701"},
{"votes":1043,"id":"1918"},
{"votes":29,"id":"3850"},
{"votes":13,"id":"59208"},
{"votes":10,"id":"11527"},
{"votes":2,"id":"12619"}],
"total":4437,"final":"1701"}}},
"precincts":
{"total":13,"reporting":13},
"name":"Phelps"},
"Thurston":
{"fips":"31173","races":
{"President":
{"":
{"votes":[
{"votes":1108,"id":"1918"},
{"votes":970,"id":"1701"},
{"votes":12,"id":"3850"},
{"votes":10,"id":"59208"},
{"votes":9,"id":"11527"},
{"votes":3,"id":"12619"}],
"total":2112,"final":"1701"}}},
"precincts":
{"total":9,"reporting":9},
"name":"Thurston"},
"Garfield":
{"fips":"31071","races":
{"President":
{"":
{"votes":[
{"votes":800,"id":"1701"},
{"votes":212,"id":"1918"},
{"votes":9,"id":"3850"},
{"votes":4,"id":"11527"},
{"votes":3,"id":"59208"},
{"votes":0,"id":"12619"}],
"total":1028,"final":"1701"}}},
"precincts":
{"total":4,"reporting":4},
"name":"Garfield"},
"Merrick":
{"fips":"31121","races":
{"President":
{"":
{"votes":[
{"votes":2356,"id":"1701"},
{"votes":978,"id":"1918"},
{"votes":24,"id":"3850"},
{"votes":18,"id":"59208"},
{"votes":7,"id":"12619"},
{"votes":7,"id":"11527"}],
"total":3390,"final":"1701"}}},
"precincts":
{"total":15,"reporting":15},
"name":"Merrick"},
"Nuckolls":
{"fips":"31129","races":
{"President":
{"":
{"votes":[
{"votes":1607,"id":"1701"},
{"votes":692,"id":"1918"},
{"votes":30,"id":"59208"},
{"votes":16,"id":"3850"},
{"votes":9,"id":"11527"},
{"votes":1,"id":"12619"}],
"total":2355,"final":"1701"}}},
"precincts":
{"total":9,"reporting":9},
"name":"Nuckolls"},
"Knox":
{"fips":"31107","races":
{"President":
{"":
{"votes":[
{"votes":2724,"id":"1701"},
{"votes":1248,"id":"1918"},
{"votes":38,"id":"3850"},
{"votes":30,"id":"59208"},
{"votes":14,"id":"11527"},
{"votes":5,"id":"12619"}],
"total":4059,"final":"1701"}}},
"precincts":
{"total":9,"reporting":9},
"name":"Knox"},
"Banner":
{"fips":"31007","races":
{"President":
{"":
{"votes":[
{"votes":341,"id":"1701"},
{"votes":61,"id":"1918"},
{"votes":5,"id":"3850"},
{"votes":1,"id":"11527"},
{"votes":0,"id":"12619"},
{"votes":0,"id":"59208"}],
"total":408,"final":"1701"}}},
"precincts":
{"total":1,"reporting":1},
"name":"Banner"},
"Hall":
{"fips":"31079","races":
{"President":
{"":
{"votes":[
{"votes":12788,"id":"1701"},
{"votes":7687,"id":"1918"},
{"votes":140,"id":"3850"},
{"votes":94,"id":"59208"},
{"votes":71,"id":"11527"},
{"votes":24,"id":"12619"}],
"total":20804,"final":"1701"}}},
"precincts":
{"total":40,"reporting":40},
"name":"Hall"},
"Scotts Bluff":
{"fips":"31157","races":
{"President":
{"":
{"votes":[
{"votes":9575,"id":"1701"},
{"votes":4645,"id":"1918"},
{"votes":105,"id":"3850"},
{"votes":62,"id":"59208"},
{"votes":51,"id":"11527"},
{"votes":14,"id":"12619"}],
"total":14452,"final":"1701"}}},
"precincts":
{"total":31,"reporting":31},
"name":"Scotts Bluff"},
"Pierce":
{"fips":"31139","races":
{"President":
{"":
{"votes":[
{"votes":2372,"id":"1701"},
{"votes":781,"id":"1918"},
{"votes":25,"id":"3850"},
{"votes":20,"id":"11527"},
{"votes":5,"id":"59208"},
{"votes":2,"id":"12619"}],
"total":3205,"final":"1701"}}},
"precincts":
{"total":6,"reporting":6},
"name":"Pierce"},
"Gosper":
{"fips":"31073","races":
{"President":
{"":
{"votes":[
{"votes":771,"id":"1701"},
{"votes":260,"id":"1918"},
{"votes":4,"id":"59208"},
{"votes":4,"id":"3850"},
{"votes":2,"id":"12619"},
{"votes":1,"id":"11527"}],
"total":1042,"final":"1701"}}},
"precincts":
{"total":4,"reporting":4},
"name":"Gosper"},
"Nance":
{"fips":"31125","races":
{"President":
{"":
{"votes":[
{"votes":1110,"id":"1701"},
{"votes":540,"id":"1918"},
{"votes":20,"id":"3850"},
{"votes":9,"id":"59208"},
{"votes":6,"id":"11527"},
{"votes":1,"id":"12619"}],
"total":1686,"final":"1701"}}},
"precincts":
{"total":6,"reporting":6},
"name":"Nance"},
"Boone":
{"fips":"31011","races":
{"President":
{"":
{"votes":[
{"votes":2042,"id":"1701"},
{"votes":742,"id":"1918"},
{"votes":17,"id":"3850"},
{"votes":12,"id":"59208"},
{"votes":6,"id":"12619"},
{"votes":5,"id":"11527"}],
"total":2824,"final":"1701"}}},
"precincts":
{"total":10,"reporting":10},
"name":"Boone"},
"Keya Paha":
{"fips":"31103","races":
{"President":
{"":
{"votes":[
{"votes":409,"id":"1701"},
{"votes":115,"id":"1918"},
{"votes":5,"id":"59208"},
{"votes":2,"id":"11527"},
{"votes":0,"id":"12619"},
{"votes":0,"id":"3850"}],
"total":531,"final":"1701"}}},
"precincts":
{"total":4,"reporting":4},
"name":"Keya Paha"},
"Pawnee":
{"fips":"31133","races":
{"President":
{"":
{"votes":[
{"votes":857,"id":"1701"},
{"votes":481,"id":"1918"},
{"votes":20,"id":"3850"},
{"votes":9,"id":"59208"},
{"votes":6,"id":"11527"},
{"votes":3,"id":"12619"}],
"total":1376,"final":"1701"}}},
"precincts":
{"total":6,"reporting":6},
"name":"Pawnee"},
"Perkins":
{"fips":"31135","races":
{"President":
{"":
{"votes":[
{"votes":1086,"id":"1701"},
{"votes":310,"id":"1918"},
{"votes":5,"id":"59208"},
{"votes":5,"id":"11527"},
{"votes":4,"id":"3850"},
{"votes":1,"id":"12619"}],
"total":1411,"final":"1701"}}},
"precincts":
{"total":3,"reporting":3},
"name":"Perkins"},
"Logan":
{"fips":"31113","races":
{"President":
{"":
{"votes":[
{"votes":327,"id":"1701"},
{"votes":81,"id":"1918"},
{"votes":3,"id":"59208"},
{"votes":3,"id":"3850"},
{"votes":1,"id":"12619"},
{"votes":0,"id":"11527"}],
"total":415,"final":"1701"}}},
"precincts":
{"total":1,"reporting":1},
"name":"Logan"},
"Thayer":
{"fips":"31169","races":
{"President":
{"":
{"votes":[
{"votes":1729,"id":"1701"},
{"votes":850,"id":"1918"},
{"votes":16,"id":"3850"},
{"votes":11,"id":"59208"},
{"votes":10,"id":"11527"},
{"votes":4,"id":"12619"}],
"total":2620,"final":"1701"}}},
"precincts":
{"total":9,"reporting":9},
"name":"Thayer"}},
"totals":
{"name":"Nebraska","precincts":
{"total":1708,"reporting":1708},
"electoral":5,"races":
{"U.S. House":
{"1":
{"votes":[
{"votes":181312,"id":"49989"},
{"votes":75922,"id":"57811"}],
"final":"49989"},
"3":
{"votes":[
{"votes":180581,"id":"30010"},
{"votes":54898,"id":"30014"}],
"final":"30010"},
"2":
{"votes":[
{"votes":139641,"id":"231"},
{"votes":127716,"id":"51569"}],
"final":"231"}},
"President":
{"":
{"votes":[
{"votes":446039,"electoral":4,"id":"1701"},
{"votes":324352,"electoral":0,"id":"1918"},
{"votes":5306,"electoral":0,"id":"3850"},
{"votes":2927,"electoral":0,"id":"59208"},
{"votes":2684,"electoral":0,"id":"11527"},
{"votes":1002,"electoral":0,"id":"12619"}],
"final":"1701"}},
"U.S. Senate":
{"":
{"votes":[
{"votes":447360,"id":"445"},
{"votes":310855,"id":"51570"},
{"votes":11079,"id":"29993"},
{"votes":7505,"id":"50446"}],
"final":"445"}},
"Initiative":
{"424-Ban Affirmative Action":
{"votes":[
{"votes":384844,"id":"2"},
{"votes":283458,"id":"3"}],
"final":"2"}}},
"abbr":"NE"}}